LICENSE
MANIFEST.in
README.md
setup.cfg
setup.py
syndicate/__init__.py
syndicate/client.py
syndicate/data.py
syndicate.egg-info/PKG-INFO
syndicate.egg-info/SOURCES.txt
syndicate.egg-info/dependency_links.txt
syndicate.egg-info/requires.txt
syndicate.egg-info/top_level.txt
syndicate/adapters/__init__.py
syndicate/adapters/aio.py
syndicate/adapters/base.py
syndicate/adapters/requests.py
test/__init__.py
test/base.py