Metadata-Version: 1.1
Name: syndicate
Version: 3.0.0
Summary: A wrapper for REST APIs
Home-page: https://github.com/mayfield/syndicate/
Author: Justin Mayfield
Author-email: tooker@gmail.com
License: MIT
Platform: UNKNOWN
Classifier: Development Status :: 5 - Production/Stable
Classifier: Intended Audience :: Developers
Classifier: License :: OSI Approved :: MIT License
Classifier: Operating System :: OS Independent
Classifier: Programming Language :: Python
Classifier: Programming Language :: Python :: 3.5
Classifier: Programming Language :: Python :: 3.6
Classifier: Programming Language :: Python :: 3.7
Classifier: Topic :: Software Development :: Libraries
